itaxotools/pygblocks/__init__.py
itaxotools/pygblocks/steps.py
itaxotools/pygblocks/types.py
itaxotools_pygblocks-0.1.0.dist-info/LICENSE.txt
itaxotools_pygblocks-0.1.0.dist-info/METADATA
itaxotools_pygblocks-0.1.0.dist-info/WHEEL
itaxotools_pygblocks-0.1.0.dist-info/top_level.txt
itaxotools_pygblocks-0.1.0.dist-info/RECORD
